coffee_list_app-1.0.15.data/scripts/cuttice
hello/__init__.py
hello/admin.py
hello/apps.py
hello/forms.py
hello/models.py
hello/views.py
hello/migrations/0001_initial.py
hello/migrations/__init__.py
hello/tests/__init__.py
hello/tests/test_admin.py
hello/tests/test_forms.py
hello/tests/test_models.py
hello/tests/tests_urls.py
hello/tests/tests_views.py
personalapp/__init__.py
personalapp/settings.py
personalapp/test_settings.py
personalapp/urls.py
personalapp/wsgi.py
coffee_list_app-1.0.15.dist-info/LICENSE
coffee_list_app-1.0.15.dist-info/METADATA
coffee_list_app-1.0.15.dist-info/WHEEL
coffee_list_app-1.0.15.dist-info/top_level.txt
coffee_list_app-1.0.15.dist-info/RECORD
