Metadata-Version: 2.1
Name: coffee-list-app
Version: 1.0.15
Summary: lists the types of coffee
Home-page: https://github.com/odhiambocuttice/app-version3
Author: odhiambo cuttice
Author-email: odhiambocuttice@gmail.com
License: UNKNOWN
Platform: UNKNOWN
Classifier: Development Status :: 3 - Alpha
Classifier: Intended Audience :: Developers
Classifier: Topic :: Software Development :: Build Tools
Classifier: License :: OSI Approved :: MIT License
Classifier: Programming Language :: Python :: 2
Classifier: Programming Language :: Python :: 2.7
Classifier: Programming Language :: Python :: 3
Classifier: Programming Language :: Python :: 3.4
Classifier: Programming Language :: Python :: 3.5
Classifier: Programming Language :: Python :: 3.6
Classifier: Programming Language :: Python :: 3.7
Requires-Python: >=2.7, !=3.0.*, !=3.1.*, !=3.2.*, !=3.3.*, <4
Requires-Dist: gunicorn
Requires-Dist: django-prometheus
Requires-Dist: sentry-sdk
Provides-Extra: test
Requires-Dist: coverage ; extra == 'test'
